pgorm.py
py_pgorm-0.0.10.dist-info/METADATA
py_pgorm-0.0.10.dist-info/WHEEL
py_pgorm-0.0.10.dist-info/top_level.txt
py_pgorm-0.0.10.dist-info/RECORD
