Metadata-Version: 2.1
Name: py-pgorm
Version: 0.0.10
Summary: simple postgres orm for python
Home-page: http://github.com/ahuigo/py-pgorm
Author: ahuigo
Author-email: ahui132@qq.com
License: MIT
Keywords: orm,python,postgres
Classifier: Development Status :: 5 - Production/Stable
Classifier: Intended Audience :: Developers
Classifier: License :: OSI Approved :: MIT License
Classifier: Natural Language :: English
Classifier: Operating System :: OS Independent
Classifier: Programming Language :: Python :: 3
Classifier: Programming Language :: Python :: 3 :: Only
Classifier: Topic :: Software Development :: Libraries :: Python Modules
Classifier: Topic :: Software Development :: Testing
Classifier: Topic :: Utilities
Requires-Python: >=3.6.1
Requires-Dist: psycopg2-binary >=2.9.9
